hm/__init__.py
hm/blocking_rule.py
hm/hm.py
healmatcher-0.0.49.dist-info/METADATA
healmatcher-0.0.49.dist-info/WHEEL
healmatcher-0.0.49.dist-info/top_level.txt
healmatcher-0.0.49.dist-info/RECORD
