Metadata-Version: 2.1
Name: healmatcher
Version: 0.0.49
Summary: Fast and simple probabilistic data matching package
Home-page: https://github.com/JosephKBS/healmatcher
Author: Joseph Shim
Author-email: <joseph.shim.rok@gmail.com>
License: UNKNOWN
Keywords: probabilistic match,probabilistic data match,splink
Platform: UNKNOWN
Classifier: Development Status :: 3 - Alpha
Classifier: Intended Audience :: Education
Classifier: Programming Language :: Python :: 2
Classifier: Programming Language :: Python :: 3
Classifier: Operating System :: MacOS :: MacOS X
Classifier: Operating System :: Microsoft :: Windows
Requires-Dist: splink
Requires-Dist: pandas
Requires-Dist: numpy
Requires-Dist: IPython
Requires-Dist: datetime
Requires-Dist: pyarrow
